LICENSE
MANIFEST.in
setup.cfg
setup.py
docs/conf.py
docs/index.rst
src/hap_py.egg-info/PKG-INFO
src/hap_py.egg-info/SOURCES.txt
src/hap_py.egg-info/dependency_links.txt
src/hap_py.egg-info/not-zip-safe
src/hap_py.egg-info/requires.txt
src/hap_py.egg-info/top_level.txt
src/happy/__init__.py
src/happy/advertiser.py
src/happy/tlv.py
src/happy/accessories/__init__.py
src/happy/accessories/accessory.py
src/happy/constants/__init__.py
src/happy/constants/accessories.py
src/happy/constants/protocol.py
src/happy/server/__init__.py
src/happy/server/hap.py
src/happy/server/orig_srp.py
src/happy/server/srp.py
src/happy/server/tlv.py
test/test_happy.py