Metadata-Version: 1.1
Name: hap-py
Version: 0.0.1
Summary: A Python implementation of the HomeKit Application Protocol.
Home-page: https://github.com/sixninetynine/happy
Author: Loren M. Carvalho
Author-email: me@loren.pizza
License: MIT license
Keywords: happy
Platform: UNKNOWN
Classifier: License :: OSI Approved :: MIT License
Classifier: Natural Language :: English
Classifier: Programming Language :: Python :: 3
Classifier: Programming Language :: Python :: 3.3
Classifier: Programming Language :: Python :: 3.4
Classifier: Programming Language :: Python :: 3.5
